Metadata-Version: 2.1
Name: CWT-MP
Version: 2
Summary: A tensorflow 2.0 Continuous Wavelet Transform with Mixed Precision Support
Home-page: UNKNOWN
License: UNKNOWN
Platform: UNKNOWN
Requires-Python: >=3.6
License-File: LICENSE
